glidertest/_version.py
glidertest/fetchers.py
glidertest/glidertest.mplstyle
glidertest/plots.py
glidertest/tools.py
glidertest/utilities.py
glidertest-0.0.1.dist-info/LICENSE
glidertest-0.0.1.dist-info/METADATA
glidertest-0.0.1.dist-info/WHEEL
glidertest-0.0.1.dist-info/top_level.txt
glidertest-0.0.1.dist-info/RECORD
