Metadata-Version: 2.1
Name: glidertest
Version: 0.0.1
Summary: Diagnostic tests of glider quality 
Maintainer-email: Callum Rollo <c.rollo@outlook.com>
License: MIT License
Project-URL: documentation, https://github.com/callumrollo/glidertest
Project-URL: homepage, https://github.com/callumrollo/glidertest
Project-URL: repository, https://github.com/callumrollo/glidertest
Classifier: Programming Language :: Python :: 3 :: Only
Classifier: Programming Language :: Python :: 3.8
Classifier: Programming Language :: Python :: 3.9
Classifier: Programming Language :: Python :: 3.10
Classifier: Programming Language :: Python :: 3.11
Classifier: Programming Language :: Python :: 3.12
Requires-Python: >=3.8
License-File: LICENSE
Requires-Dist: netcdf4
Requires-Dist: pooch
Requires-Dist: xarray
Requires-Dist: numpy
Requires-Dist: matplotlib
Requires-Dist: pandas
Requires-Dist: seaborn
Requires-Dist: scipy
Requires-Dist: skyfield
Requires-Dist: gsw
Requires-Dist: sgp4>=2.14
Requires-Dist: cartopy
